modas/MODAS.py
modas/__init__.py
modas/coloc.py
modas/contrast.py
modas/genoidx.py
modas/gwas_cmd.py
modas/mr.py
modas/multiprocess.py
modas/phenorm.py
modas/prescreen.py
modas/regiongwas.py
modas/visual.py
modas/utils/CMplot.r
modas/utils/GAPIT.library.R
modas/utils/Matrix_1.6-5.tar.gz
modas/utils/cluster_one-1.0.jar
modas/utils/gapit_functions.txt
modas/utils/gemma
modas/utils/plink
modas/utils/rMVP_1.0.6_modify.tar.gz
modas/utils/assets/bootstrap/css/bootstrap.min.css
modas/utils/assets/bootstrap/js/bootstrap.min.js
modas/utils/assets/css/modas.css
modas/utils/assets/fonts/FontAwesome.otf
modas/utils/assets/fonts/font-awesome.min.css
modas/utils/assets/fonts/fontawesome-webfont.eot
modas/utils/assets/fonts/fontawesome-webfont.svg
modas/utils/assets/fonts/fontawesome-webfont.ttf
modas/utils/assets/fonts/fontawesome-webfont.woff
modas/utils/assets/fonts/fontawesome-webfont.woff2
modas/utils/assets/js/jquery.min.js
modas/utils/assets/js/modas.js
modas/utils/assets/js/test.js
modas-2.2.1.dist-info/METADATA
modas-2.2.1.dist-info/WHEEL
modas-2.2.1.dist-info/entry_points.txt
modas-2.2.1.dist-info/licenses/LICENSE
modas-2.2.1.dist-info/RECORD
