Metadata-Version: 2.3
Name: MODAS
Version: 2.2.1
Summary: MODAS: Multi-omics data association study
Project-URL: Documentation, https://modas-bio.github.io/
Project-URL: Repository, https://github.com/liusy-jz/MODAS.git
Author-email: syliu <songyu__liu@163.com>, CrazyHsu <crazyhsu9527@gmail.com>
Maintainer-email: syliu <songyu__liu@163.com>
License:                     GNU GENERAL PUBLIC LICENSE
License-File: LICENSE
Keywords: GWAS,Mendelian randomization,contrastive PCA,multi-omics
Classifier: License :: OSI Approved :: GNU General Public License v3 (GPLv3)
Classifier: Programming Language :: Python :: 3
Classifier: Programming Language :: Python :: 3.8
Requires-Python: >=3.8
Requires-Dist: bioframe
Requires-Dist: cython
Requires-Dist: image-match3
Requires-Dist: matplotlib
Requires-Dist: numpy
Requires-Dist: pandas
Requires-Dist: pandas-plink
Requires-Dist: pyranges
Requires-Dist: rpy2
Requires-Dist: scikit-learn
Requires-Dist: scipy
Requires-Dist: statsmodels
Requires-Dist: yattag==1.14.0
